libname/__init__.py
libname/csvedit.py
csvedit-0.0.1.dist-info/METADATA
csvedit-0.0.1.dist-info/WHEEL
csvedit-0.0.1.dist-info/top_level.txt
csvedit-0.0.1.dist-info/RECORD
